rss_to_graphql/__init__.py
rss_to_graphql/__main__.py
rss_to_graphql/schema.py
rss_to_graphql/template.py
rss_to_graphql-0.0.1.dist-info/LICENSE
rss_to_graphql-0.0.1.dist-info/METADATA
rss_to_graphql-0.0.1.dist-info/WHEEL
rss_to_graphql-0.0.1.dist-info/top_level.txt
rss_to_graphql-0.0.1.dist-info/RECORD
