Metadata-Version: 2.1
Name: rss-to-graphql
Version: 0.0.1
Summary: A microservice proxy to convert an rss feed to a GraphQL API endpoint
Home-page: UNKNOWN
Author: Kuda Savanhu
Maintainer: Kuda Savanhu
License: UNKNOWN
Keywords: python,rss to graphql,requests,rss,graphql
Platform: UNKNOWN
Classifier: Development Status :: 3 - Alpha
Classifier: License :: OSI Approved :: MIT License
Classifier: Programming Language :: Python :: 3
Classifier: Programming Language :: Python :: 3.6
Classifier: Programming Language :: Python :: 3.7
Classifier: Programming Language :: Python :: 3.8
Classifier: Programming Language :: Python :: 3.9
Classifier: Operating System :: OS Independent
Classifier: Environment :: Console
Classifier: Intended Audience :: Developers
Classifier: Topic :: Utilities
Classifier: Topic :: Internet :: WWW/HTTP :: WSGI :: Server
Classifier: Topic :: Software Development :: Libraries :: Python Modules
Requires-Dist: Flask (>=1.1.2)
Requires-Dist: Flask-GraphQL (>=2.0.1)
Requires-Dist: Flask-Sockets (>=0.2.1)
Requires-Dist: graphql-ws (>=0.3.1)
Requires-Dist: gevent (>=1.5.0)
Requires-Dist: gevent-websocket (>=0.10.1)
Requires-Dist: graphene (>=2.1.8)
Requires-Dist: Rx (>=1.6.1)
